hupper/__init__.py
hupper/cli.py
hupper/interfaces.py
hupper/ipc.py
hupper/logger.py
hupper/polling.py
hupper/reloader.py
hupper/utils.py
hupper/watchdog.py
hupper/watchman.py
hupper/winapi.py
hupper/worker.py
hupper-1.11.dist-info/LICENSE.txt
hupper-1.11.dist-info/METADATA
hupper-1.11.dist-info/WHEEL
hupper-1.11.dist-info/entry_points.txt
hupper-1.11.dist-info/top_level.txt
hupper-1.11.dist-info/RECORD
